hawk_scanner/__init__.py
hawk_scanner/main.py
hawk_scanner/commands/__init__.py
hawk_scanner/commands/couchdb.py
hawk_scanner/commands/firebase.py
hawk_scanner/commands/fs.py
hawk_scanner/commands/gcs.py
hawk_scanner/commands/gdrive.py
hawk_scanner/commands/gdrive_workspace.py
hawk_scanner/commands/mongodb.py
hawk_scanner/commands/mysql.py
hawk_scanner/commands/postgresql.py
hawk_scanner/commands/redis.py
hawk_scanner/commands/s3.py
hawk_scanner/commands/slack.py
hawk_scanner/commands/text.py
hawk_scanner/internals/__init__.py
hawk_scanner/internals/system.py
hawk_scanner-0.3.37.dist-info/licenses/LICENSE
hawk_scanner-0.3.37.dist-info/METADATA
hawk_scanner-0.3.37.dist-info/WHEEL
hawk_scanner-0.3.37.dist-info/entry_points.txt
hawk_scanner-0.3.37.dist-info/top_level.txt
hawk_scanner-0.3.37.dist-info/RECORD
