Metadata-Version: 2.4
Name: hawk_scanner
Version: 0.3.37
Summary: A powerful scanner to scan your Filesystem, S3, MongoDB, MySQL, PostgreSQL, Redis, Slack, Google Cloud Storage and Firebase storage for PII and sensitive data using text and OCR analysis. Hawk-eye can also analyse supports most of the file types like docx, xlsx, pptx, pdf, jpg, png, gif, zip, tar, rar, etc.
Home-page: https://github.com/rohitcoder/hawk-eye
Author: Rohit Kumar
Author-email: 
License: Apache License 2.0
Keywords: pii secrets sensitive-data cybersecurity scanner
Classifier: Development Status :: 3 - Alpha
Classifier: Intended Audience :: Developers
Classifier: Topic :: Software Development :: Build Tools
Classifier: Programming Language :: Python :: 3
Classifier: Programming Language :: Python :: 3.7
License-File: LICENSE
Requires-Dist: boto3
Requires-Dist: PyYAML
Requires-Dist: jmespath
Requires-Dist: rich
Requires-Dist: mysql-connector-python
Requires-Dist: pymysql
Requires-Dist: redis
Requires-Dist: firebase-admin
Requires-Dist: slack-sdk
Requires-Dist: google-cloud-core
Requires-Dist: google-cloud-storage
Requires-Dist: pymongo==4.6.3
Requires-Dist: tinydb==4.8.0
Requires-Dist: pytesseract
Requires-Dist: Pillow
Requires-Dist: python-docx
Requires-Dist: openpyxl
Requires-Dist: PyPDF2
Requires-Dist: setuptools
Requires-Dist: patool
Requires-Dist: pydrive2
Requires-Dist: appdirs
Requires-Dist: tqdm
Requires-Dist: funcy
Requires-Dist: fsspec
Requires-Dist: opencv-python
Provides-Extra: dev
Requires-Dist: twine>=4.0.2; extra == "dev"
Dynamic: author
Dynamic: classifier
Dynamic: description
Dynamic: description-content-type
Dynamic: home-page
Dynamic: keywords
Dynamic: license
Dynamic: license-file
Dynamic: provides-extra
Dynamic: requires-dist
Dynamic: summary
